urlify/__init__.py
urlify_simple-0.1.1.dist-info/licenses/LICENSE
urlify_simple-0.1.1.dist-info/METADATA
urlify_simple-0.1.1.dist-info/WHEEL
urlify_simple-0.1.1.dist-info/top_level.txt
urlify_simple-0.1.1.dist-info/RECORD
