Metadata-Version: 2.4
Name: urlify-simple
Version: 0.1.1
Summary: A simple URL shortener package using TinyURL
Home-page: https://github.com/TheRaj71
Author: The Raj
Author-email: theraj05@duck.com
Classifier: Programming Language :: Python :: 3
Classifier: License :: OSI Approved :: MIT License
Classifier: Operating System :: OS Independent
Requires-Python: >=3.6
License-File: LICENSE
Requires-Dist: requests>=2.25.1
Dynamic: author
Dynamic: author-email
Dynamic: classifier
Dynamic: description
Dynamic: description-content-type
Dynamic: home-page
Dynamic: license-file
Dynamic: requires-dist
Dynamic: requires-python
Dynamic: summary
